poverty/__init__.py
poverty/index.py
poverty-7.2.dist-info/DESCRIPTION.rst
poverty-7.2.dist-info/METADATA
poverty-7.2.dist-info/RECORD
poverty-7.2.dist-info/WHEEL
poverty-7.2.dist-info/metadata.json
poverty-7.2.dist-info/top_level.txt
