Metadata-Version: 2.0
Name: poverty
Version: 7.2
Summary: A Python Package to calculate indexes related to poverty and inequality.
Home-page: https://github.com/ronak-07/poverty
Author: Ronak Sisodia
Author-email: ronaksisodia07@gmail.com
License: MIT
Keywords: Poverty,Inequality,Economics,Gini Coefficient,Lorenz Curve
Platform: UNKNOWN
Classifier: Development Status :: 3 - Alpha
Classifier: Operating System :: OS Independent
Classifier: Intended Audience :: Education
Classifier: License :: OSI Approved :: MIT License
Classifier: Programming Language :: Python :: 3
Classifier: Programming Language :: Python :: 3.2
Classifier: Programming Language :: Python :: 3.3
Classifier: Programming Language :: Python :: 3.4
Classifier: Programming Language :: Python :: 3.5
Classifier: Programming Language :: Python :: 3.6
Requires-Dist: numpy
Requires-Dist: matplotlib
